secureutils/__init__.py
secureutils/certificates.py
secureutils/crypto.py
secureutils/database.py
secureutils/fileops.py
secureutils/http.py
secureutils/obfuscator.py
secureutils/threadpool.py
secureutils/winapi.py
tests/__init__.py
tests/test_certificates.py
tests/test_crypto.py
tests/test_database.py
tests/test_fileops.py
tests/test_http.py
tests/test_obfuscator.py
tests/test_runtime_crypto.py
tests/test_threadpool.py
tests/test_winapi.py
secureutils-0.1.0.dist-info/METADATA
secureutils-0.1.0.dist-info/WHEEL
secureutils-0.1.0.dist-info/top_level.txt
secureutils-0.1.0.dist-info/RECORD
